litex.regon-1.0.6-py3.9-nspkg.pth
litex/regon/__init__.py
litex/regon/envelopes.py
litex.regon-1.0.6.dist-info/METADATA
litex.regon-1.0.6.dist-info/WHEEL
litex.regon-1.0.6.dist-info/namespace_packages.txt
litex.regon-1.0.6.dist-info/top_level.txt
litex.regon-1.0.6.dist-info/RECORD
