Metadata-Version: 2.1
Name: litex.regon
Version: 1.0.6
Summary: An API for accessing a Polish REGON database
Home-page: http://litexservice.pl
Author: Michal Wegrzynek
Author-email: mwegrzynek@litex.pl
License: GPL
Keywords: regon soap database
Platform: UNKNOWN
Classifier: Programming Language :: Python
Classifier: Topic :: Database :: Front-Ends
Requires-Dist: setuptools
Requires-Dist: requests
Requires-Dist: lxml
